aiida_gudhi/__init__.py
aiida_gudhi/calculations/__init__.py
aiida_gudhi/calculations/cubical.py
aiida_gudhi/calculations/rips.py
aiida_gudhi/calculations/test_rips.py
aiida_gudhi/data/__init__.py
aiida_gudhi/data/rips.py
aiida_gudhi/parsers/__init__.py
aiida_gudhi/parsers/barcode.py
aiida_gudhi/parsers/rips.py
aiida_gudhi/parsers/test_barcode.py
aiida_gudhi/tests/__init__.py
aiida_gudhi/workflows/__init__.py
aiida_gudhi-0.1.0a3.data/scripts/cli.py
aiida_gudhi-0.1.0a3.dist-info/METADATA
aiida_gudhi-0.1.0a3.dist-info/RECORD
aiida_gudhi-0.1.0a3.dist-info/WHEEL
aiida_gudhi-0.1.0a3.dist-info/entry_points.txt
aiida_gudhi-0.1.0a3.dist-info/top_level.txt
