Metadata-Version: 2.1
Name: aiida-gudhi
Version: 0.1.0a3
Summary: AiiDA plugin for the [GUDHI](http://gudhi.gforge.inria.fr/) library for topological data analysis.
Home-page: https://github.com/ltalirz/aiida-gudhi
Author: Leopold Talirz
Author-email: leopold.talirz@gmail.com
License: MIT
Platform: UNKNOWN
Classifier: Programming Language :: Python
Requires-Dist: aiida (>=0.11)
Provides-Extra: docs
Requires-Dist: sphinx; extra == 'docs'
Provides-Extra: pre-commit
Requires-Dist: pre-commit; extra == 'pre-commit'
Requires-Dist: yapf; extra == 'pre-commit'
Requires-Dist: prospector; extra == 'pre-commit'
Requires-Dist: pylint; extra == 'pre-commit'
Provides-Extra: testing
Requires-Dist: aiida-core[testing]; extra == 'testing'
